odoo/addons/migration_wordpress_blog/__init__.py
odoo/addons/migration_wordpress_blog/__manifest__.py
odoo/addons/migration_wordpress_blog/models/__init__.py
odoo/addons/migration_wordpress_blog/models/migration_import_wordpress.py
odoo/addons/migration_wordpress_blog/static/description/1.jpg
odoo/addons/migration_wordpress_blog/static/description/index.html
odoo/addons/migration_wordpress_blog/views/migration_import_wordpress_views.xml
odoo14_addon_migration_wordpress_blog-14.0.1.0.0.dist-info/METADATA
odoo14_addon_migration_wordpress_blog-14.0.1.0.0.dist-info/WHEEL
odoo14_addon_migration_wordpress_blog-14.0.1.0.0.dist-info/top_level.txt
odoo14_addon_migration_wordpress_blog-14.0.1.0.0.dist-info/RECORD
