Metadata-Version: 2.1
Name: odoo14-addon-migration-wordpress-blog
Version: 14.0.1.0.0
Summary: Migration Wordpress Blog, Sythil Tech module migrated to Odoo14
Home-page: UNKNOWN
Author: Coopdevs
License: AGPL-3
Platform: UNKNOWN
Classifier: Programming Language :: Python
Classifier: Framework :: Odoo
Classifier: Framework :: Odoo :: 14.0
Classifier: License :: OSI Approved :: GNU Affero General Public License v3
Requires-Python: >=3.6
Requires-Dist: odoo14-addon-migration-wordpress
Requires-Dist: odoo (<14.1dev,>=14.0a)
